edmgr/__init__.py
edmgr/auth.py
edmgr/client.py
edmgr/config.py
edmgr/download.py
edmgr/edmgrcli.py
edmgr/exceptions.py
edmgr/formatters.py
edmgr/requester.py
edmgr/utils.py
edmgr-1.3.1.dist-info/LICENSE
edmgr-1.3.1.dist-info/METADATA
edmgr-1.3.1.dist-info/WHEEL
edmgr-1.3.1.dist-info/entry_points.txt
edmgr-1.3.1.dist-info/RECORD
