Metadata-Version: 2.3
Name: edmgr
Version: 1.3.1
Summary: Entitlements and Download Manager
License: MIT
Author: Digital Delivery
Author-email: Digital-Delivery@arm.com
Maintainer: Arm Ltd.
Requires-Python: >=3.10,<3.14
Classifier: Natural Language :: English
Classifier: Intended Audience :: Developers
Classifier: Intended Audience :: Information Technology
Classifier: Environment :: Console
Classifier: Development Status :: 4 - Beta
Classifier: License :: OSI Approved :: MIT License
Classifier: Programming Language :: Python :: 3
Classifier: Programming Language :: Python :: 3.10
Classifier: Programming Language :: Python :: 3.11
Classifier: Programming Language :: Python :: 3.12
Classifier: Programming Language :: Python :: 3.13
Classifier: Programming Language :: Python :: 3 :: Only
Classifier: Operating System :: OS Independent
Requires-Dist: click (>=8.2.1,<9.0.0)
Requires-Dist: cryptography (>=45.0.4,<46.0.0)
Requires-Dist: msal (>=1.32.3,<2.0.0)
Requires-Dist: pyjwt (>=2.10.1,<3.0.0)
Requires-Dist: requests (>=2.32.4,<3.0.0)
Requires-Dist: tabulate (>=0.9.0,<0.10.0)
Requires-Dist: tox (>=4.25.0,<5.0.0)
Requires-Dist: tqdm (>=4.67.1,<5.0.0)
